rackfocus/__init__.py
rackfocus/compilation.py
rackfocus/database.py
rackfocus/models.py
rackfocus/run.py
rackfocus-1.2.0.dist-info/LICENSE
rackfocus-1.2.0.dist-info/METADATA
rackfocus-1.2.0.dist-info/WHEEL
rackfocus-1.2.0.dist-info/entry_points.txt
rackfocus-1.2.0.dist-info/top_level.txt
rackfocus-1.2.0.dist-info/RECORD
