Metadata-Version: 2.1
Name: rackfocus
Version: 1.2.0
Summary: CLI utility to download and compile IMDb datasets into an SQLite database.
Home-page: https://github.com/Antrikshy/Rackfocus
Author: Antriksh Yadav
Author-email: antrikshy@gmail.com
License: MIT
Platform: UNKNOWN
Classifier: Programming Language :: Python :: 3
Classifier: License :: OSI Approved :: MIT License
Classifier: Operating System :: OS Independent
Classifier: Topic :: Database
License-File: LICENSE
